{
  "language_code": "hil",
  "language_name": "Hiligaynon",
  "language_native": "Hiligaynon",
  "language_family": "Austronesian",
  "entry_count": 107,
  "complete_entries": 7,
  "entries": [
    {
      "word": "kamusta",
      "ipa": "/ka.ˈmus.ta/",
      "meaning_en": "hello",
      "pos": "noun",
      "example": ""
    },
    {
      "word": "salamat",
      "ipa": "/sa.ˈla.mat/",
      "meaning_en": "thank you",
      "pos": "noun",
      "example": ""
    },
    {
      "word": "huo",
      "ipa": "/hu.ˈo/",
      "meaning_en": "yes",
      "pos": "noun",
      "example": ""
    },
    {
      "word": "indi",
      "ipa": "/ˈin.di/",
      "meaning_en": "no",
      "pos": "noun",
      "example": ""
    },
    {
      "word": "isa",
      "ipa": "/ˈi.sa/",
      "meaning_en": "one",
      "pos": "numeral",
      "example": ""
    },
    {
      "word": "duha",
      "ipa": "/ˈdu.ha/",
      "meaning_en": "two",
      "pos": "numeral",
      "example": ""
    },
    {
      "word": "tatlo",
      "ipa": "/ˈtat.lo/",
      "meaning_en": "three",
      "pos": "numeral",
      "example": ""
    },
    {
      "word": "[TODO:hil:goodbye]",
      "ipa": "",
      "meaning_en": "goodbye",
      "pos": "noun",
      "example": "",
      "_needs_translation": true
    },
    {
      "word": "[TODO:hil:good morning]",
      "ipa": "",
      "meaning_en": "good morning",
      "pos": "noun",
      "example": "",
      "_needs_translation": true
    },
    {
      "word": "[TODO:hil:good evening]",
      "ipa": "",
      "meaning_en": "good evening",
      "pos": "noun",
      "example": "",
      "_needs_translation": true
    },
    {
      "word": "[TODO:hil:please]",
      "ipa": "",
      "meaning_en": "please",
      "pos": "noun",
      "example": "",
      "_needs_translation": true
    },
    {
      "word": "[TODO:hil:excuse me]",
      "ipa": "",
      "meaning_en": "excuse me",
      "pos": "noun",
      "example": "",
      "_needs_translation": true
    },
    {
      "word": "[TODO:hil:sorry]",
      "ipa": "",
      "meaning_en": "sorry",
      "pos": "noun",
      "example": "",
      "_needs_translation": true
    },
    {
      "word": "[TODO:hil:four]",
      "ipa": "",
      "meaning_en": "four",
      "pos": "numeral",
      "example": "",
      "_needs_translation": true
    },
    {
      "word": "[TODO:hil:five]",
      "ipa": "",
      "meaning_en": "five",
      "pos": "numeral",
      "example": "",
      "_needs_translation": true
    },
    {
      "word": "[TODO:hil:six]",
      "ipa": "",
      "meaning_en": "six",
      "pos": "numeral",
      "example": "",
      "_needs_translation": true
    },
    {
      "word": "[TODO:hil:seven]",
      "ipa": "",
      "meaning_en": "seven",
      "pos": "numeral",
      "example": "",
      "_needs_translation": true
    },
    {
      "word": "[TODO:hil:eight]",
      "ipa": "",
      "meaning_en": "eight",
      "pos": "numeral",
      "example": "",
      "_needs_translation": true
    },
    {
      "word": "[TODO:hil:nine]",
      "ipa": "",
      "meaning_en": "nine",
      "pos": "numeral",
      "example": "",
      "_needs_translation": true
    },
    {
      "word": "[TODO:hil:ten]",
      "ipa": "",
      "meaning_en": "ten",
      "pos": "numeral",
      "example": "",
      "_needs_translation": true
    },
    {
      "word": "[TODO:hil:hundred]",
      "ipa": "",
      "meaning_en": "hundred",
      "pos": "numeral",
      "example": "",
      "_needs_translation": true
    },
    {
      "word": "[TODO:hil:thousand]",
      "ipa": "",
      "meaning_en": "thousand",
      "pos": "numeral",
      "example": "",
      "_needs_translation": true
    },
    {
      "word": "[TODO:hil:mother]",
      "ipa": "",
      "meaning_en": "mother",
      "pos": "noun",
      "example": "",
      "_needs_translation": true
    },
    {
      "word": "[TODO:hil:father]",
      "ipa": "",
      "meaning_en": "father",
      "pos": "noun",
      "example": "",
      "_needs_translation": true
    },
    {
      "word": "[TODO:hil:sister]",
      "ipa": "",
      "meaning_en": "sister",
      "pos": "noun",
      "example": "",
      "_needs_translation": true
    },
    {
      "word": "[TODO:hil:brother]",
      "ipa": "",
      "meaning_en": "brother",
      "pos": "noun",
      "example": "",
      "_needs_translation": true
    },
    {
      "word": "[TODO:hil:child]",
      "ipa": "",
      "meaning_en": "child",
      "pos": "noun",
      "example": "",
      "_needs_translation": true
    },
    {
      "word": "[TODO:hil:grandmother]",
      "ipa": "",
      "meaning_en": "grandmother",
      "pos": "noun",
      "example": "",
      "_needs_translation": true
    },
    {
      "word": "[TODO:hil:grandfather]",
      "ipa": "",
      "meaning_en": "grandfather",
      "pos": "noun",
      "example": "",
      "_needs_translation": true
    },
    {
      "word": "[TODO:hil:husband]",
      "ipa": "",
      "meaning_en": "husband",
      "pos": "noun",
      "example": "",
      "_needs_translation": true
    },
    {
      "word": "[TODO:hil:wife]",
      "ipa": "",
      "meaning_en": "wife",
      "pos": "noun",
      "example": "",
      "_needs_translation": true
    },
    {
      "word": "[TODO:hil:family]",
      "ipa": "",
      "meaning_en": "family",
      "pos": "noun",
      "example": "",
      "_needs_translation": true
    },
    {
      "word": "[TODO:hil:head]",
      "ipa": "",
      "meaning_en": "head",
      "pos": "noun",
      "example": "",
      "_needs_translation": true
    },
    {
      "word": "[TODO:hil:hand]",
      "ipa": "",
      "meaning_en": "hand",
      "pos": "noun",
      "example": "",
      "_needs_translation": true
    },
    {
      "word": "[TODO:hil:eye]",
      "ipa": "",
      "meaning_en": "eye",
      "pos": "noun",
      "example": "",
      "_needs_translation": true
    },
    {
      "word": "[TODO:hil:mouth]",
      "ipa": "",
      "meaning_en": "mouth",
      "pos": "noun",
      "example": "",
      "_needs_translation": true
    },
    {
      "word": "[TODO:hil:ear]",
      "ipa": "",
      "meaning_en": "ear",
      "pos": "noun",
      "example": "",
      "_needs_translation": true
    },
    {
      "word": "[TODO:hil:nose]",
      "ipa": "",
      "meaning_en": "nose",
      "pos": "noun",
      "example": "",
      "_needs_translation": true
    },
    {
      "word": "[TODO:hil:foot]",
      "ipa": "",
      "meaning_en": "foot",
      "pos": "noun",
      "example": "",
      "_needs_translation": true
    },
    {
      "word": "[TODO:hil:heart]",
      "ipa": "",
      "meaning_en": "heart",
      "pos": "noun",
      "example": "",
      "_needs_translation": true
    },
    {
      "word": "[TODO:hil:blood]",
      "ipa": "",
      "meaning_en": "blood",
      "pos": "noun",
      "example": "",
      "_needs_translation": true
    },
    {
      "word": "[TODO:hil:bone]",
      "ipa": "",
      "meaning_en": "bone",
      "pos": "noun",
      "example": "",
      "_needs_translation": true
    },
    {
      "word": "[TODO:hil:water]",
      "ipa": "",
      "meaning_en": "water",
      "pos": "noun",
      "example": "",
      "_needs_translation": true
    },
    {
      "word": "[TODO:hil:fire]",
      "ipa": "",
      "meaning_en": "fire",
      "pos": "noun",
      "example": "",
      "_needs_translation": true
    },
    {
      "word": "[TODO:hil:earth]",
      "ipa": "",
      "meaning_en": "earth",
      "pos": "noun",
      "example": "",
      "_needs_translation": true
    },
    {
      "word": "[TODO:hil:sky]",
      "ipa": "",
      "meaning_en": "sky",
      "pos": "noun",
      "example": "",
      "_needs_translation": true
    },
    {
      "word": "[TODO:hil:sun]",
      "ipa": "",
      "meaning_en": "sun",
      "pos": "noun",
      "example": "",
      "_needs_translation": true
    },
    {
      "word": "[TODO:hil:moon]",
      "ipa": "",
      "meaning_en": "moon",
      "pos": "noun",
      "example": "",
      "_needs_translation": true
    },
    {
      "word": "[TODO:hil:star]",
      "ipa": "",
      "meaning_en": "star",
      "pos": "noun",
      "example": "",
      "_needs_translation": true
    },
    {
      "word": "[TODO:hil:rain]",
      "ipa": "",
      "meaning_en": "rain",
      "pos": "noun",
      "example": "",
      "_needs_translation": true
    },
    {
      "word": "[TODO:hil:wind]",
      "ipa": "",
      "meaning_en": "wind",
      "pos": "noun",
      "example": "",
      "_needs_translation": true
    },
    {
      "word": "[TODO:hil:tree]",
      "ipa": "",
      "meaning_en": "tree",
      "pos": "noun",
      "example": "",
      "_needs_translation": true
    },
    {
      "word": "[TODO:hil:rice]",
      "ipa": "",
      "meaning_en": "rice",
      "pos": "noun",
      "example": "",
      "_needs_translation": true
    },
    {
      "word": "[TODO:hil:bread]",
      "ipa": "",
      "meaning_en": "bread",
      "pos": "noun",
      "example": "",
      "_needs_translation": true
    },
    {
      "word": "[TODO:hil:fish]",
      "ipa": "",
      "meaning_en": "fish",
      "pos": "noun",
      "example": "",
      "_needs_translation": true
    },
    {
      "word": "[TODO:hil:meat]",
      "ipa": "",
      "meaning_en": "meat",
      "pos": "noun",
      "example": "",
      "_needs_translation": true
    },
    {
      "word": "[TODO:hil:fruit]",
      "ipa": "",
      "meaning_en": "fruit",
      "pos": "noun",
      "example": "",
      "_needs_translation": true
    },
    {
      "word": "[TODO:hil:milk]",
      "ipa": "",
      "meaning_en": "milk",
      "pos": "noun",
      "example": "",
      "_needs_translation": true
    },
    {
      "word": "[TODO:hil:salt]",
      "ipa": "",
      "meaning_en": "salt",
      "pos": "noun",
      "example": "",
      "_needs_translation": true
    },
    {
      "word": "[TODO:hil:sugar]",
      "ipa": "",
      "meaning_en": "sugar",
      "pos": "noun",
      "example": "",
      "_needs_translation": true
    },
    {
      "word": "[TODO:hil:egg]",
      "ipa": "",
      "meaning_en": "egg",
      "pos": "noun",
      "example": "",
      "_needs_translation": true
    },
    {
      "word": "[TODO:hil:oil]",
      "ipa": "",
      "meaning_en": "oil",
      "pos": "noun",
      "example": "",
      "_needs_translation": true
    },
    {
      "word": "[TODO:hil:eat]",
      "ipa": "",
      "meaning_en": "eat",
      "pos": "verb",
      "example": "",
      "_needs_translation": true
    },
    {
      "word": "[TODO:hil:drink]",
      "ipa": "",
      "meaning_en": "drink",
      "pos": "verb",
      "example": "",
      "_needs_translation": true
    },
    {
      "word": "[TODO:hil:sleep]",
      "ipa": "",
      "meaning_en": "sleep",
      "pos": "verb",
      "example": "",
      "_needs_translation": true
    },
    {
      "word": "[TODO:hil:walk]",
      "ipa": "",
      "meaning_en": "walk",
      "pos": "verb",
      "example": "",
      "_needs_translation": true
    },
    {
      "word": "[TODO:hil:speak]",
      "ipa": "",
      "meaning_en": "speak",
      "pos": "verb",
      "example": "",
      "_needs_translation": true
    },
    {
      "word": "[TODO:hil:see]",
      "ipa": "",
      "meaning_en": "see",
      "pos": "verb",
      "example": "",
      "_needs_translation": true
    },
    {
      "word": "[TODO:hil:hear]",
      "ipa": "",
      "meaning_en": "hear",
      "pos": "verb",
      "example": "",
      "_needs_translation": true
    },
    {
      "word": "[TODO:hil:give]",
      "ipa": "",
      "meaning_en": "give",
      "pos": "verb",
      "example": "",
      "_needs_translation": true
    },
    {
      "word": "[TODO:hil:come]",
      "ipa": "",
      "meaning_en": "come",
      "pos": "verb",
      "example": "",
      "_needs_translation": true
    },
    {
      "word": "[TODO:hil:go]",
      "ipa": "",
      "meaning_en": "go",
      "pos": "verb",
      "example": "",
      "_needs_translation": true
    },
    {
      "word": "[TODO:hil:know]",
      "ipa": "",
      "meaning_en": "know",
      "pos": "verb",
      "example": "",
      "_needs_translation": true
    },
    {
      "word": "[TODO:hil:want]",
      "ipa": "",
      "meaning_en": "want",
      "pos": "verb",
      "example": "",
      "_needs_translation": true
    },
    {
      "word": "[TODO:hil:love]",
      "ipa": "",
      "meaning_en": "love",
      "pos": "verb",
      "example": "",
      "_needs_translation": true
    },
    {
      "word": "[TODO:hil:work]",
      "ipa": "",
      "meaning_en": "work",
      "pos": "verb",
      "example": "",
      "_needs_translation": true
    },
    {
      "word": "[TODO:hil:live]",
      "ipa": "",
      "meaning_en": "live",
      "pos": "verb",
      "example": "",
      "_needs_translation": true
    },
    {
      "word": "[TODO:hil:big]",
      "ipa": "",
      "meaning_en": "big",
      "pos": "adjective",
      "example": "",
      "_needs_translation": true
    },
    {
      "word": "[TODO:hil:small]",
      "ipa": "",
      "meaning_en": "small",
      "pos": "adjective",
      "example": "",
      "_needs_translation": true
    },
    {
      "word": "[TODO:hil:good]",
      "ipa": "",
      "meaning_en": "good",
      "pos": "adjective",
      "example": "",
      "_needs_translation": true
    },
    {
      "word": "[TODO:hil:bad]",
      "ipa": "",
      "meaning_en": "bad",
      "pos": "adjective",
      "example": "",
      "_needs_translation": true
    },
    {
      "word": "[TODO:hil:hot]",
      "ipa": "",
      "meaning_en": "hot",
      "pos": "adjective",
      "example": "",
      "_needs_translation": true
    },
    {
      "word": "[TODO:hil:cold]",
      "ipa": "",
      "meaning_en": "cold",
      "pos": "adjective",
      "example": "",
      "_needs_translation": true
    },
    {
      "word": "[TODO:hil:new]",
      "ipa": "",
      "meaning_en": "new",
      "pos": "adjective",
      "example": "",
      "_needs_translation": true
    },
    {
      "word": "[TODO:hil:old]",
      "ipa": "",
      "meaning_en": "old",
      "pos": "adjective",
      "example": "",
      "_needs_translation": true
    },
    {
      "word": "[TODO:hil:beautiful]",
      "ipa": "",
      "meaning_en": "beautiful",
      "pos": "adjective",
      "example": "",
      "_needs_translation": true
    },
    {
      "word": "[TODO:hil:strong]",
      "ipa": "",
      "meaning_en": "strong",
      "pos": "adjective",
      "example": "",
      "_needs_translation": true
    },
    {
      "word": "[TODO:hil:today]",
      "ipa": "",
      "meaning_en": "today",
      "pos": "noun",
      "example": "",
      "_needs_translation": true
    },
    {
      "word": "[TODO:hil:tomorrow]",
      "ipa": "",
      "meaning_en": "tomorrow",
      "pos": "noun",
      "example": "",
      "_needs_translation": true
    },
    {
      "word": "[TODO:hil:yesterday]",
      "ipa": "",
      "meaning_en": "yesterday",
      "pos": "noun",
      "example": "",
      "_needs_translation": true
    },
    {
      "word": "[TODO:hil:morning]",
      "ipa": "",
      "meaning_en": "morning",
      "pos": "noun",
      "example": "",
      "_needs_translation": true
    },
    {
      "word": "[TODO:hil:night]",
      "ipa": "",
      "meaning_en": "night",
      "pos": "noun",
      "example": "",
      "_needs_translation": true
    },
    {
      "word": "[TODO:hil:year]",
      "ipa": "",
      "meaning_en": "year",
      "pos": "noun",
      "example": "",
      "_needs_translation": true
    },
    {
      "word": "[TODO:hil:month]",
      "ipa": "",
      "meaning_en": "month",
      "pos": "noun",
      "example": "",
      "_needs_translation": true
    },
    {
      "word": "[TODO:hil:week]",
      "ipa": "",
      "meaning_en": "week",
      "pos": "noun",
      "example": "",
      "_needs_translation": true
    },
    {
      "word": "[TODO:hil:day]",
      "ipa": "",
      "meaning_en": "day",
      "pos": "noun",
      "example": "",
      "_needs_translation": true
    },
    {
      "word": "[TODO:hil:hour]",
      "ipa": "",
      "meaning_en": "hour",
      "pos": "noun",
      "example": "",
      "_needs_translation": true
    },
    {
      "word": "[TODO:hil:house]",
      "ipa": "",
      "meaning_en": "house",
      "pos": "noun",
      "example": "",
      "_needs_translation": true
    },
    {
      "word": "[TODO:hil:village]",
      "ipa": "",
      "meaning_en": "village",
      "pos": "noun",
      "example": "",
      "_needs_translation": true
    },
    {
      "word": "[TODO:hil:city]",
      "ipa": "",
      "meaning_en": "city",
      "pos": "noun",
      "example": "",
      "_needs_translation": true
    },
    {
      "word": "[TODO:hil:market]",
      "ipa": "",
      "meaning_en": "market",
      "pos": "noun",
      "example": "",
      "_needs_translation": true
    },
    {
      "word": "[TODO:hil:school]",
      "ipa": "",
      "meaning_en": "school",
      "pos": "noun",
      "example": "",
      "_needs_translation": true
    },
    {
      "word": "[TODO:hil:church]",
      "ipa": "",
      "meaning_en": "church",
      "pos": "noun",
      "example": "",
      "_needs_translation": true
    },
    {
      "word": "[TODO:hil:river]",
      "ipa": "",
      "meaning_en": "river",
      "pos": "noun",
      "example": "",
      "_needs_translation": true
    },
    {
      "word": "[TODO:hil:mountain]",
      "ipa": "",
      "meaning_en": "mountain",
      "pos": "noun",
      "example": "",
      "_needs_translation": true
    },
    {
      "word": "[TODO:hil:road]",
      "ipa": "",
      "meaning_en": "road",
      "pos": "noun",
      "example": "",
      "_needs_translation": true
    },
    {
      "word": "[TODO:hil:field]",
      "ipa": "",
      "meaning_en": "field",
      "pos": "noun",
      "example": "",
      "_needs_translation": true
    }
  ]
}